LICENSE
MANIFEST.in
Makefile
README.md
requirements-dev.txt
requirements.txt
setup.py
s2kindle.egg-info/PKG-INFO
s2kindle.egg-info/SOURCES.txt
s2kindle.egg-info/dependency_links.txt
s2kindle.egg-info/entry_points.txt
s2kindle.egg-info/requires.txt
s2kindle.egg-info/top_level.txt
send_to_kindle/__init__.py
send_to_kindle/cli.py
send_to_kindle/assets/article-template.html
send_to_kindle/converter/__init__.py
send_to_kindle/converter/mobi_converter.py
send_to_kindle/downloader/__init__.py
send_to_kindle/downloader/article.py
send_to_kindle/downloader/article_downloader.py
send_to_kindle/downloader/content_extractor.py
send_to_kindle/downloader/image_downloader.py
send_to_kindle/sender/__init__.py
send_to_kindle/sender/email_sender.py