Metadata-Version: 2.1
Name: s2kindle
Version: 0.3.0
Summary: Send web articles to your kindle!
Home-page: https://github.com/fferegrino/send-to-kindle
Author: Antonio Feregrino
Author-email: antonio.feregrino@gmail.com
License: UNKNOWN
Platform: UNKNOWN
